akms_logs/__init__.py
akms_logs/main.py
akms_logs-0.1.0.dist-info/LICENSE
akms_logs-0.1.0.dist-info/METADATA
akms_logs-0.1.0.dist-info/WHEEL
akms_logs-0.1.0.dist-info/top_level.txt
akms_logs-0.1.0.dist-info/RECORD
