Metadata-Version: 2.1
Name: akms-logs
Version: 0.1.0
Summary: A wrapper logger package for akms logging
Home-page: https://github.com/apinanyogaratnam/akms-logs-package
Author: apinanyogaratnam
Author-email: apinanapinan@icloud.com
Classifier: Programming Language :: Python :: 3
Classifier: License :: OSI Approved :: MIT License
Classifier: Operating System :: OS Independent
Requires-Python: >=3.10.4
License-File: LICENSE
